<?xml version="1.0" encoding="utf-8"?>
<odoo>

  <record model="ir.module.category" id="module_queue_management_category">
    <field name="name">Queue Management</field>
  </record>

  <record id="group_queue_management_branch_agent" model="res.groups">
    <field name="name">Branch Agent</field>
    <field name="category_id" ref="module_queue_management_category"/>
  </record>

  <record id="group_queue_management_branch_manager" model="res.groups">
    <field name="name">Branch Manager</field>
    <field name="category_id" ref="module_queue_management_category"/>
  </record>
  
  <record id="group_queue_management_admin" model="res.groups">
    <field name="name">Queue Administrator</field>
    <field name="implied_ids" eval="[(4, ref('group_queue_management_branch_manager'))]"/>
    <field name="category_id" ref="module_queue_management_category"/>
  </record>
  
</odoo>
